transfermarkt_api_wrapper/__init__.py
transfermarkt_api_wrapper/clubs/__init__.py
transfermarkt_api_wrapper/clubs/clubs.py
transfermarkt_api_wrapper/competitions/__init__.py
transfermarkt_api_wrapper/competitions/competitions.py
transfermarkt_api_wrapper/main.py
transfermarkt_api_wrapper/pandas/__init__.py
transfermarkt_api_wrapper/pandas/competitions/__init__.py
transfermarkt_api_wrapper/pandas/competitions/competitions.py
transfermarkt_api_wrapper/pandas/players/__init__.py
transfermarkt_api_wrapper/pandas/players/players.py
transfermarkt_api_wrapper/players/__init__.py
transfermarkt_api_wrapper/players/players.py
transfermarkt_api_wrapper-0.1.8.dist-info/METADATA
transfermarkt_api_wrapper-0.1.8.dist-info/WHEEL
transfermarkt_api_wrapper-0.1.8.dist-info/RECORD
