Metadata-Version: 2.1
Name: transfermarkt-api-wrapper
Version: 0.1.8
Summary: Lightweight wrapper for Transfermarkt API
License: MIT
Author: Felipe Allegretti
Author-email: felipe@allegretti.me
Requires-Python: >=3.9,<4.0
Classifier: License :: OSI Approved :: MIT License
Classifier: Programming Language :: Python :: 3
Classifier: Programming Language :: Python :: 3.9
Classifier: Programming Language :: Python :: 3.10
Classifier: Programming Language :: Python :: 3.11
Requires-Dist: pandas (>=1.5.3,<2.0.0)
Requires-Dist: requests (>=2.28.2,<3.0.0)
Requires-Dist: tqdm (>=4.65.0,<5.0.0)
